predictable/__init__.py
predictable/__main__.py
predictable/cli/__init__.py
predictable/cli/scaffold.py
predictable/core/__init__.py
predictable/core/discounting.py
predictable/core/flows.py
predictable/core/io.py
predictable/core/lookup.py
predictable/core/model.py
predictable/core/precision.py
predictable/core/rating_factors.py
predictable/engine/__init__.py
predictable/engine/run.py
predictable-0.0.2.dist-info/METADATA
predictable-0.0.2.dist-info/WHEEL
predictable-0.0.2.dist-info/entry_points.txt
predictable-0.0.2.dist-info/licenses/LICENSE
predictable-0.0.2.dist-info/RECORD
