Metadata-Version: 2.1
Name: predictable
Version: 0.0.2
Summary: A framework for actuarial modelling.
Project-URL: Bug Tracker, https://github.com/RatulMaharaj/predictable/issues
Project-URL: homepage, https://github.com/RatulMaharaj/predictable
Project-URL: documentation, https://predictable.readthedocs.io
Author-email: Ratul Maharaj <ratulmaharaj@gmail.com>
License: MIT License
License-File: LICENSE
Keywords: actuarial,financial services,modelling,predictable,python
Classifier: License :: OSI Approved :: MIT License
Classifier: Operating System :: OS Independent
Classifier: Programming Language :: Python :: 3
Requires-Python: >=3.11
Requires-Dist: numpy==1.24.3
Requires-Dist: pandas==2.0.1
Requires-Dist: pydantic==1.10.7
